[
  {
    "name": "Plomería",
    "subCategoryArray": [
      "Destape de cañerías",
      "Instalación de grifería y sanitarios",
      "Reparación de fugas",
      "Mantenimiento de calentadores"
    ]
  },
  {
    "name": "Electricidad",
    "subCategoryArray": [
      "Instalaciones eléctricas residenciales",
      "Reparación de cortocircuitos",
      "Instalación de paneles solares",
      "Sistemas de iluminación y domótica"
    ]
  },
  {
    "name": "Paseo de Perros",
    "subCategoryArray": [
      "Paseos individuales personalizados",
      "Paseos grupales para socialización",
      "Cuidado a domicilio (Pet Sitting)",
      "Adiestramiento básico en paseo"
    ]
  },
  {
    "name": "Pintura",
    "subCategoryArray": [
      "Pintura de interiores",
      "Pintura de fachadas",
      "Aplicación de estuco y texturizados",
      "Impermeabilización de superficies"
    ]
  },
  {
    "name": "Jardinería",
    "subCategoryArray": [
      "Mantenimiento de césped y jardines",
      "Poda de árboles y arbustos",
      "Diseño de paisajes",
      "Instalación de sistemas de riego"
    ]
  },
  {
    "name": "Aseo y Limpieza",
    "subCategoryArray": [
      "Aseo doméstico por días",
      "Limpieza profunda de espacios",
      "Limpieza de tapetes y muebles",
      "Desinfección de ambientes"
    ]
  }
]